chesstutor/__init__.py
chesstutor/__main__.py
chesstutor/chesstutor.py
chesstutor_Ceasar-0.0.6.dist-info/LICENSE.txt
chesstutor_Ceasar-0.0.6.dist-info/METADATA
chesstutor_Ceasar-0.0.6.dist-info/WHEEL
chesstutor_Ceasar-0.0.6.dist-info/top_level.txt
chesstutor_Ceasar-0.0.6.dist-info/RECORD
