Metadata-Version: 2.1
Name: chesstutor-Ceasar
Version: 0.0.6
Summary: Play chess on the command line.
Home-page: https://github.com/Ceasar/chesstutor
Author: Ceasar Bautista
Author-email: cbautista2010@gmail.com
License: UNKNOWN
Platform: UNKNOWN
Classifier: Programming Language :: Python :: 3
Classifier: License :: OSI Approved :: MIT License
Classifier: Operating System :: OS Independent
Requires-Python: >=3.6
Requires-Dist: click
Requires-Dist: python-chess
